i2c_slave.sv
module i2c_slave(
	inout sda,
	inout scl
	);
	
	localparam ADDRESS = 7'b0101010;
	
	localparam READ_ADDR = 0;
	localparam SEND_ACK = 1;
	localparam READ_DATA = 2;
	localparam WRITE_DATA = 3;
	localparam SEND_ACK2 = 4;
	
	reg [7:0] addr;
	reg [7:0] counter;
	reg [7:0] state = 0;
  reg [7:0] data_in = 8'b01101101;
  reg [7:0] data_out = 0;
	reg sda_out = 0;
	reg sda_in = 0;
	reg start = 0;
	reg wr_enable = 0;
	
	assign sda = (wr_enable == 1) ? sda_out : 'bz;
	
	always @(negedge sda) begin
		if ((start == 0) && (scl == 1)) begin
			start <= 1;	
			counter <= 7;
		end
	end
	
	always @(posedge sda) begin
		if ((start == 1) && (scl == 1)) begin
			state <= READ_ADDR;
			start <= 0;
			wr_enable <= 0;
		end
	end
	
	always @(posedge scl) begin
		if (start == 1) begin
			case(state)
				READ_ADDR: begin
					addr[counter] <= sda;
					if(counter == 0) state <= SEND_ACK;
					else counter <= counter - 1;					
				end
				
				SEND_ACK: begin
					if(addr[7:1] == ADDRESS) begin
						counter <= 7;
						if(addr[0] == 0) begin 
							state <= READ_DATA;
						end
						else state <= WRITE_DATA;
					end
				end
				
				READ_DATA: begin
					data_out[counter] <= sda;
					if(counter == 0) begin
						state <= SEND_ACK2;
					end else counter <= counter - 1;
				end
				
				SEND_ACK2: begin
					state <= READ_ADDR;					
				end
				
				WRITE_DATA: begin
					if(counter == 0) state <= READ_ADDR;
					else counter <= counter - 1;		
				end
				
			endcase
		end
	end
	
	always @(negedge scl) begin
		case(state)
			
			READ_ADDR: begin
				wr_enable <= 0;			
			end
			
			SEND_ACK: begin
				sda_out <= 0;
				wr_enable <= 1;	
			end
			
			READ_DATA: begin
				wr_enable <= 0;
			end
			
			WRITE_DATA: begin
				sda_out <= data_in[counter];
				wr_enable <= 1;
			end
			
			SEND_ACK2: begin
				sda_out <= 0;
				wr_enable <= 1;
			end
		endcase
	end
endmodule

i2c_master.sv
module i2c_master(clk,rst,addr,data_in,en,rw,data_out,ready,sda,scl);
	input  clk,rst,en,rw;
    input  [6:0] addr;
    input  [7:0] data_in;
    output reg [7:0] data_out;
	output reg ready;
	inout sda;
	inout wire scl;

	parameter IDLE = 0,
	START = 1,
	ADDRESS = 2,
	READ_ACK = 3,
	WRITE_DATA = 4,
	WRITE_ACK = 5,
	READ_DATA = 6,
	READ_ACK2 = 7,
	STOP = 8,
	CYCLES = 4;

	reg [7:0] state;
	reg [7:0] saved_addr;
	reg [7:0] saved_data;
    reg [7:0] counter;
    reg [7:0] counter_clk = 0;
	reg wr_enable;
	reg sda_out;
	reg scl_enable = 0;
	reg scl_clk = 1;

	assign ready = ((rst == 0) && (state == IDLE)) ? 1 : 0;
  assign scl = (scl_enable == 0 ) ? 1 : scl_clk;
	assign sda = (wr_enable == 1) ? sda_out : 'bz;
	
	always @(posedge clk) begin
      if (counter_clk == (CYCLES/2) - 1) begin
			scl_clk <= ~scl_clk;
			counter_clk <= 0;
		end
		else 
          counter_clk <= counter_clk + 1;
	end 
	
  always @(negedge scl_clk, posedge rst) begin
		if(rst == 1) begin
			scl_enable <= 0;
		end else begin
			if ((state == IDLE) || (state == START) || (state == STOP)) begin
				scl_enable <= 0;
			end else begin
				scl_enable <= 1;
			end
		end
	
	end


  always @(posedge scl_clk, posedge rst) begin
		if(rst == 1) begin
			state <= IDLE;
		end		
		else begin
			case(state)
			
				IDLE: begin
                  if (en) begin
						state <= START;
						saved_addr <= {addr, rw};
						saved_data <= data_in;
					end
					else state <= IDLE;
				end

				START: begin
					counter <= 7;
					state <= ADDRESS;
				end

				ADDRESS: begin
					if (counter == 0) begin 
						state <= READ_ACK;
					end else counter <= counter - 1;
				end

				READ_ACK: begin
					if (sda == 0) begin
						counter <= 7;
						if(saved_addr[0] == 0) state <= WRITE_DATA;
						else state <= READ_DATA;
					end else state <= STOP;
				end

				WRITE_DATA: begin
					if(counter == 0) begin
						state <= READ_ACK2;
					end else counter <= counter - 1;
				end
				
				READ_ACK2: begin
					if ((sda == 0) && (en == 1)) state <= IDLE;
					else state <= STOP;
				end

				READ_DATA: begin
					data_out[counter] <= sda;
					if (counter == 0) state <= WRITE_ACK;
					else counter <= counter - 1;
				end
				
				WRITE_ACK: begin
					state <= STOP;
				end

				STOP: begin
					state <= IDLE;
				end
			endcase
		end
	end
	
  always @(negedge scl_clk, posedge rst) begin
		if(rst == 1) begin
			wr_enable <= 1;
			sda_out <= 1;
		end else begin
			case(state)
				
				START: begin
					wr_enable <= 1;
					sda_out <= 0;
				end
				
				ADDRESS: begin
					sda_out <= saved_addr[counter];
				end
				
				READ_ACK: begin
					wr_enable <= 0;
				end
				
				WRITE_DATA: begin 
					wr_enable <= 1;
					sda_out <= saved_data[counter];
				end
				
				WRITE_ACK: begin
					wr_enable <= 1;
					sda_out <= 0;
				end
				
				READ_DATA: begin
					wr_enable <= 0;				
				end
				
				STOP: begin
					wr_enable <= 1;
					sda_out <= 1;
				end
			endcase
		end
	end

endmodule

i2c_tb.sv
module i2c_tb;

	// Inputs
	reg clk;
	reg rst;
	reg [6:0] addr;
	reg [7:0] data_in;
	reg en;
	reg rw;

	// Outputs
	wire [7:0] data_out;
	wire ready;
	wire sda;
	wire scl;

	i2c_master master (
		.clk(clk), 
		.rst(rst), 
		.addr(addr), 
		.data_in(data_in), 
		.en(en), 
		.rw(rw), 
		.data_out(data_out), 
		.ready(ready), 
		.sda(sda), 
		.scl(scl)
	);
	
		
	i2c_slave slave (
    .sda(sda), 
    .scl(scl)
    );
	
  initial begin
  $dumpfile("i2c_protocal.vcd");
  $dumpvars(0,i2c_tb);
  end
  
  always #1 clk=~clk;
	
	initial begin
		clk = 0;
		rst = 1;
		#100;
        
		rst = 0;		
		addr = 7'b0101010;
		data_in = 8'b10101010;
		rw = 1;	
		en = 1;
      #10
      	
      
		en = 0;
				
		#500
		$finish;
    end
endmodule

i2c_protocal.vcd
$date
	Sat Sep 27 14:23:26 2025
$end
$version
	Icarus Verilog
$end
$timescale
	1s
$end
$scope module i2c_tb $end
$var wire 1 ! sda $end
$var wire 1 " scl $end
$var wire 1 # ready $end
$var wire 8 $ data_out [7:0] $end
$var reg 7 % addr [6:0] $end
$var reg 1 & clk $end
$var reg 8 ' data_in [7:0] $end
$var reg 1 ( en $end
$var reg 1 ) rst $end
$var reg 1 * rw $end
$scope module master $end
$var wire 7 + addr [6:0] $end
$var wire 1 & clk $end
$var wire 8 , data_in [7:0] $end
$var wire 1 ( en $end
$var wire 1 ) rst $end
$var wire 1 * rw $end
$var wire 1 ! sda $end
$var wire 1 " scl $end
$var wire 1 # ready $end
$var parameter 32 - ADDRESS $end
$var parameter 32 . CYCLES $end
$var parameter 32 / IDLE $end
$var parameter 32 0 READ_ACK $end
$var parameter 32 1 READ_ACK2 $end
$var parameter 32 2 READ_DATA $end
$var parameter 32 3 START $end
$var parameter 32 4 STOP $end
$var parameter 32 5 WRITE_ACK $end
$var parameter 32 6 WRITE_DATA $end
$var reg 8 7 counter [7:0] $end
$var reg 8 8 counter_clk [7:0] $end
$var reg 8 9 data_out [7:0] $end
$var reg 8 : saved_addr [7:0] $end
$var reg 8 ; saved_data [7:0] $end
$var reg 1 < scl_clk $end
$var reg 1 = scl_enable $end
$var reg 1 > sda_out $end
$var reg 8 ? state [7:0] $end
$var reg 1 @ wr_enable $end
$upscope $end
$scope module slave $end
$var wire 1 " scl $end
$var wire 1 ! sda $end
$var parameter 7 A ADDRESS $end
$var parameter 32 B READ_ADDR $end
$var parameter 32 C READ_DATA $end
$var parameter 32 D SEND_ACK $end
$var parameter 32 E SEND_ACK2 $end
$var parameter 32 F WRITE_DATA $end
$var reg 8 G addr [7:0] $end
$var reg 8 H counter [7:0] $end
$var reg 8 I data_in [7:0] $end
$var reg 8 J data_out [7:0] $end
$var reg 1 K sda_in $end
$var reg 1 L sda_out $end
$var reg 1 M start $end
$var reg 8 N state [7:0] $end
$var reg 1 O wr_enable $end
$upscope $end
$upscope $end
$enddefinitions $end
$comment Show the parameter values. $end
$dumpall
b11 F
b100 E
b1 D
b10 C
b0 B
b101010 A
b100 6
b101 5
b1000 4
b1 3
b110 2
b111 1
b11 0
b0 /
b100 .
b10 -
$end
#0
$dumpvars
0O
b0 N
0M
0L
0K
b0 J
b1101101 I
bx H
bx G
1@
b0 ?
1>
0=
1<
bx ;
bx :
bx 9
b0 8
bx 7
bx ,
bx +
x*
1)
x(
bx '
0&
bx %
bx $
0#
1"
1!
$end
#1
b1 8
1&
#2
0&
#3
b0 8
0<
1&
#4
0&
#5
b1 8
1&
#6
0&
#7
b0 8
1<
1&
#8
0&
#9
b1 8
1&
#10
0&
#11
b0 8
0<
1&
#12
0&
#13
b1 8
1&
#14
0&
#15
b0 8
1<
1&
#16
0&
#17
b1 8
1&
#18
0&
#19
b0 8
0<
1&
#20
0&
#21
b1 8
1&
#22
0&
#23
b0 8
1<
1&
#24
0&
#25
b1 8
1&
#26
0&
#27
b0 8
0<
1&
#28
0&
#29
b1 8
1&
#30
0&
#31
b0 8
1<
1&
#32
0&
#33
b1 8
1&
#34
0&
#35
b0 8
0<
1&
#36
0&
#37
b1 8
1&
#38
0&
#39
b0 8
1<
1&
#40
0&
#41
b1 8
1&
#42
0&
#43
b0 8
0<
1&
#44
0&
#45
b1 8
1&
#46
0&
#47
b0 8
1<
1&
#48
0&
#49
b1 8
1&
#50
0&
#51
b0 8
0<
1&
#52
0&
#53
b1 8
1&
#54
0&
#55
b0 8
1<
1&
#56
0&
#57
b1 8
1&
#58
0&
#59
b0 8
0<
1&
#60
0&
#61
b1 8
1&
#62
0&
#63
b0 8
1<
1&
#64
0&
#65
b1 8
1&
#66
0&
#67
b0 8
0<
1&
#68
0&
#69
b1 8
1&
#70
0&
#71
b0 8
1<
1&
#72
0&
#73
b1 8
1&
#74
0&
#75
b0 8
0<
1&
#76
0&
#77
b1 8
1&
#78
0&
#79
b0 8
1<
1&
#80
0&
#81
b1 8
1&
#82
0&
#83
b0 8
0<
1&
#84
0&
#85
b1 8
1&
#86
0&
#87
b0 8
1<
1&
#88
0&
#89
b1 8
1&
#90
0&
#91
b0 8
0<
1&
#92
0&
#93
b1 8
1&
#94
0&
#95
b0 8
1<
1&
#96
0&
#97
b1 8
1&
#98
0&
#99
b0 8
0<
1&
#100
1#
0&
1(
1*
b10101010 '
b10101010 ,
b101010 %
b101010 +
0)
#101
b1 8
1&
#102
0&
#103
0#
b10101010 ;
b1010101 :
b1 ?
b0 8
1<
1&
#104
0&
#105
b1 8
1&
#106
0&
#107
b111 H
1M
0!
0>
b0 8
0<
1&
#108
0&
#109
b1 8
1&
#110
0&
0(
#111
b10 ?
b111 7
b0 8
1<
1&
#112
0&
#113
b1 8
1&
#114
0&
#115
0"
1=
b0 8
0<
1&
#116
0&
#117
b1 8
1&
#118
0&
#119
b110 H
b0xxxxxxx G
b110 7
1"
b0 8
1<
1&
#120
0&
#121
b1 8
1&
#122
0&
#123
1!
1>
0"
b0 8
0<
1&
#124
0&
#125
b1 8
1&
#126
0&
#127
b101 H
b1xxxxxx G
b101 7
1"
b0 8
1<
1&
#128
0&
#129
b1 8
1&
#130
0&
#131
0!
0>
0"
b0 8
0<
1&
#132
0&
#133
b1 8
1&
#134
0&
#135
b100 H
b10xxxxx G
b100 7
1"
b0 8
1<
1&
#136
0&
#137
b1 8
1&
#138
0&
#139
1!
1>
0"
b0 8
0<
1&
#140
0&
#141
b1 8
1&
#142
0&
#143
b11 H
b101xxxx G
b11 7
1"
b0 8
1<
1&
#144
0&
#145
b1 8
1&
#146
0&
#147
0!
0>
0"
b0 8
0<
1&
#148
0&
#149
b1 8
1&
#150
0&
#151
b10 H
b1010xxx G
b10 7
1"
b0 8
1<
1&
#152
0&
#153
b1 8
1&
#154
0&
#155
1!
1>
0"
b0 8
0<
1&
#156
0&
#157
b1 8
1&
#158
0&
#159
b1 H
b10101xx G
b1 7
1"
b0 8
1<
1&
#160
0&
#161
b1 8
1&
#162
0&
#163
0!
0>
0"
b0 8
0<
1&
#164
0&
#165
b1 8
1&
#166
0&
#167
b0 H
b101010x G
b0 7
1"
b0 8
1<
1&
#168
0&
#169
b1 8
1&
#170
0&
#171
1!
1>
0"
b0 8
0<
1&
#172
0&
#173
b1 8
1&
#174
0&
#175
b1 N
b1010101 G
b11 ?
1"
b0 8
1<
1&
#176
0&
#177
b1 8
1&
#178
0&
#179
0!
1O
0@
0"
b0 8
0<
1&
#180
0&
#181
b1 8
1&
#182
0&
#183
b11 N
b111 H
b110 ?
b111 7
1"
b0 8
1<
1&
#184
0&
#185
b1 8
1&
#186
0&
#187
0"
b0 8
0<
1&
#188
0&
#189
b1 8
1&
#190
0&
#191
b110 H
b110 7
b0xxxxxxx $
b0xxxxxxx 9
1"
b0 8
1<
1&
#192
0&
#193
b1 8
1&
#194
0&
#195
1!
1L
0"
b0 8
0<
1&
#196
0&
#197
b1 8
1&
#198
0&
#199
b101 H
b101 7
b1xxxxxx $
b1xxxxxx 9
1"
b0 8
1<
1&
#200
0&
#201
b1 8
1&
#202
0&
#203
0"
b0 8
0<
1&
#204
0&
#205
b1 8
1&
#206
0&
#207
b100 H
b100 7
b11xxxxx $
b11xxxxx 9
1"
b0 8
1<
1&
#208
0&
#209
b1 8
1&
#210
0&
#211
0!
0L
0"
b0 8
0<
1&
#212
0&
#213
b1 8
1&
#214
0&
#215
b11 H
b11 7
b110xxxx $
b110xxxx 9
1"
b0 8
1<
1&
#216
0&
#217
b1 8
1&
#218
0&
#219
1!
1L
0"
b0 8
0<
1&
#220
0&
#221
b1 8
1&
#222
0&
#223
b10 H
b10 7
b1101xxx $
b1101xxx 9
1"
b0 8
1<
1&
#224
0&
#225
b1 8
1&
#226
0&
#227
0"
b0 8
0<
1&
#228
0&
#229
b1 8
1&
#230
0&
#231
b1 H
b1 7
b11011xx $
b11011xx 9
1"
b0 8
1<
1&
#232
0&
#233
b1 8
1&
#234
0&
#235
0!
0L
0"
b0 8
0<
1&
#236
0&
#237
b1 8
1&
#238
0&
#239
b0 H
b0 7
b110110x $
b110110x 9
1"
b0 8
1<
1&
#240
0&
#241
b1 8
1&
#242
0&
#243
1!
1L
0"
b0 8
0<
1&
#244
0&
#245
b1 8
1&
#246
0&
#247
b0 N
b101 ?
b1101101 $
b1101101 9
1"
b0 8
1<
1&
#248
0&
#249
b1 8
1&
#250
0&
#251
0!
0O
0>
1@
0"
b0 8
0<
1&
#252
0&
#253
b1 8
1&
#254
0&
#255
b1 N
b1010100 G
b1000 ?
1"
b0 8
1<
1&
#256
0&
#257
b1 8
1&
#258
0&
#259
b111 H
0M
b10 N
1!
0O
0L
1>
0=
1"
b0 8
0<
1&
#260
0&
#261
b1 8
1&
#262
0&
#263
1#
b0 ?
b0 8
1<
1&
#264
0&
#265
b1 8
1&
#266
0&
#267
b0 8
0<
1&
#268
0&
#269
b1 8
1&
#270
0&
#271
b0 8
1<
1&
#272
0&
#273
b1 8
1&
#274
0&
#275
b0 8
0<
1&
#276
0&
#277
b1 8
1&
#278
0&
#279
b0 8
1<
1&
#280
0&
#281
b1 8
1&
#282
0&
#283
b0 8
0<
1&
#284
0&
#285
b1 8
1&
#286
0&
#287
b0 8
1<
1&
#288
0&
#289
b1 8
1&
#290
0&
#291
b0 8
0<
1&
#292
0&
#293
b1 8
1&
#294
0&
#295
b0 8
1<
1&
#296
0&
#297
b1 8
1&
#298
0&
#299
b0 8
0<
1&
#300
0&
#301
b1 8
1&
#302
0&
#303
b0 8
1<
1&
#304
0&
#305
b1 8
1&
#306
0&
#307
b0 8
0<
1&
#308
0&
#309
b1 8
1&
#310
0&
#311
b0 8
1<
1&
#312
0&
#313
b1 8
1&
#314
0&
#315
b0 8
0<
1&
#316
0&
#317
b1 8
1&
#318
0&
#319
b0 8
1<
1&
#320
0&
#321
b1 8
1&
#322
0&
#323
b0 8
0<
1&
#324
0&
#325
b1 8
1&
#326
0&
#327
b0 8
1<
1&
#328
0&
#329
b1 8
1&
#330
0&
#331
b0 8
0<
1&
#332
0&
#333
b1 8
1&
#334
0&
#335
b0 8
1<
1&
#336
0&
#337
b1 8
1&
#338
0&
#339
b0 8
0<
1&
#340
0&
#341
b1 8
1&
#342
0&
#343
b0 8
1<
1&
#344
0&
#345
b1 8
1&
#346
0&
#347
b0 8
0<
1&
#348
0&
#349
b1 8
1&
#350
0&
#351
b0 8
1<
1&
#352
0&
#353
b1 8
1&
#354
0&
#355
b0 8
0<
1&
#356
0&
#357
b1 8
1&
#358
0&
#359
b0 8
1<
1&
#360
0&
#361
b1 8
1&
#362
0&
#363
b0 8
0<
1&
#364
0&
#365
b1 8
1&
#366
0&
#367
b0 8
1<
1&
#368
0&
#369
b1 8
1&
#370
0&
#371
b0 8
0<
1&
#372
0&
#373
b1 8
1&
#374
0&
#375
b0 8
1<
1&
#376
0&
#377
b1 8
1&
#378
0&
#379
b0 8
0<
1&
#380
0&
#381
b1 8
1&
#382
0&
#383
b0 8
1<
1&
#384
0&
#385
b1 8
1&
#386
0&
#387
b0 8
0<
1&
#388
0&
#389
b1 8
1&
#390
0&
#391
b0 8
1<
1&
#392
0&
#393
b1 8
1&
#394
0&
#395
b0 8
0<
1&
#396
0&
#397
b1 8
1&
#398
0&
#399
b0 8
1<
1&
#400
0&
#401
b1 8
1&
#402
0&
#403
b0 8
0<
1&
#404
0&
#405
b1 8
1&
#406
0&
#407
b0 8
1<
1&
#408
0&
#409
b1 8
1&
#410
0&
#411
b0 8
0<
1&
#412
0&
#413
b1 8
1&
#414
0&
#415
b0 8
1<
1&
#416
0&
#417
b1 8
1&
#418
0&
#419
b0 8
0<
1&
#420
0&
#421
b1 8
1&
#422
0&
#423
b0 8
1<
1&
#424
0&
#425
b1 8
1&
#426
0&
#427
b0 8
0<
1&
#428
0&
#429
b1 8
1&
#430
0&
#431
b0 8
1<
1&
#432
0&
#433
b1 8
1&
#434
0&
#435
b0 8
0<
1&
#436
0&
#437
b1 8
1&
#438
0&
#439
b0 8
1<
1&
#440
0&
#441
b1 8
1&
#442
0&
#443
b0 8
0<
1&
#444
0&
#445
b1 8
1&
#446
0&
#447
b0 8
1<
1&
#448
0&
#449
b1 8
1&
#450
0&
#451
b0 8
0<
1&
#452
0&
#453
b1 8
1&
#454
0&
#455
b0 8
1<
1&
#456
0&
#457
b1 8
1&
#458
0&
#459
b0 8
0<
1&
#460
0&
#461
b1 8
1&
#462
0&
#463
b0 8
1<
1&
#464
0&
#465
b1 8
1&
#466
0&
#467
b0 8
0<
1&
#468
0&
#469
b1 8
1&
#470
0&
#471
b0 8
1<
1&
#472
0&
#473
b1 8
1&
#474
0&
#475
b0 8
0<
1&
#476
0&
#477
b1 8
1&
#478
0&
#479
b0 8
1<
1&
#480
0&
#481
b1 8
1&
#482
0&
#483
b0 8
0<
1&
#484
0&
#485
b1 8
1&
#486
0&
#487
b0 8
1<
1&
#488
0&
#489
b1 8
1&
#490
0&
#491
b0 8
0<
1&
#492
0&
#493
b1 8
1&
#494
0&
#495
b0 8
1<
1&
#496
0&
#497
b1 8
1&
#498
0&
#499
b0 8
0<
1&
#500
0&
#501
b1 8
1&
#502
0&
#503
b0 8
1<
1&
#504
0&
#505
b1 8
1&
#506
0&
#507
b0 8
0<
1&
#508
0&
#509
b1 8
1&
#510
0&
#511
b0 8
1<
1&
#512
0&
#513
b1 8
1&
#514
0&
#515
b0 8
0<
1&
#516
0&
#517
b1 8
1&
#518
0&
#519
b0 8
1<
1&
#520
0&
#521
b1 8
1&
#522
0&
#523
b0 8
0<
1&
#524
0&
#525
b1 8
1&
#526
0&
#527
b0 8
1<
1&
#528
0&
#529
b1 8
1&
#530
0&
#531
b0 8
0<
1&
#532
0&
#533
b1 8
1&
#534
0&
#535
b0 8
1<
1&
#536
0&
#537
b1 8
1&
#538
0&
#539
b0 8
0<
1&
#540
0&
#541
b1 8
1&
#542
0&
#543
b0 8
1<
1&
#544
0&
#545
b1 8
1&
#546
0&
#547
b0 8
0<
1&
#548
0&
#549
b1 8
1&
#550
0&
#551
b0 8
1<
1&
#552
0&
#553
b1 8
1&
#554
0&
#555
b0 8
0<
1&
#556
0&
#557
b1 8
1&
#558
0&
#559
b0 8
1<
1&
#560
0&
#561
b1 8
1&
#562
0&
#563
b0 8
0<
1&
#564
0&
#565
b1 8
1&
#566
0&
#567
b0 8
1<
1&
#568
0&
#569
b1 8
1&
#570
0&
#571
b0 8
0<
1&
#572
0&
#573
b1 8
1&
#574
0&
#575
b0 8
1<
1&
#576
0&
#577
b1 8
1&
#578
0&
#579
b0 8
0<
1&
#580
0&
#581
b1 8
1&
#582
0&
#583
b0 8
1<
1&
#584
0&
#585
b1 8
1&
#586
0&
#587
b0 8
0<
1&
#588
0&
#589
b1 8
1&
#590
0&
#591
b0 8
1<
1&
#592
0&
#593
b1 8
1&
#594
0&
#595
b0 8
0<
1&
#596
0&
#597
b1 8
1&
#598
0&
#599
b0 8
1<
1&
#600
0&
#601
b1 8
1&
#602
0&
#603
b0 8
0<
1&
#604
0&
#605
b1 8
1&
#606
0&
#607
b0 8
1<
1&
#608
0&
#609
b1 8
1&
